mqsc/pyqdmi.pyi
mqsc/py.typed
mqsc/pyqdmi.cpython-311-darwin.so
mqsc/pyqdmi_qiskit/backend.py
mqsc/pyqdmi_qiskit/job.py
mqsc/pyqdmi_qiskit/__init__.py
mqsc_pyqdmi-0.1.3.dist-info/RECORD
mqsc_pyqdmi-0.1.3.dist-info/WHEEL
mqsc_pyqdmi-0.1.3.dist-info/METADATA
mqsc_pyqdmi-0.1.3.dist-info/licenses/LICENSE.txt
